BulkImageResizer/BulkImageResizer.py
BulkImageResizer/__init__.py
BulkImageResizer-1.0.4.dist-info/METADATA
BulkImageResizer-1.0.4.dist-info/RECORD
BulkImageResizer-1.0.4.dist-info/WHEEL
BulkImageResizer-1.0.4.dist-info/top_level.txt
