Metadata-Version: 2.1
Name: BulkImageResizer
Version: 1.0.4
Summary: Resizes any number of images, written to use in responsive front end web development
Home-page: https://github.com/suhrabjan/BulkImageResizer
Author: Suhrab Kurbanov
Author-email: sir.suhrab@gmail.com
License: UNKNOWN
Platform: UNKNOWN
Classifier: Programming Language :: Python :: 3
Classifier: License :: OSI Approved :: MIT License
Classifier: Operating System :: OS Independent
Requires-Dist: Pillow
